gungor_package/AnExamplePackageForTheBook.py
gungor_package/__init__.py
gungor_package-0.0.4.dist-info/METADATA
gungor_package-0.0.4.dist-info/WHEEL
gungor_package-0.0.4.dist-info/top_level.txt
gungor_package-0.0.4.dist-info/RECORD
