Metadata-Version: 2.1
Name: gungor-package
Version: 0.0.4
Summary: An Example Package For The Book
Author: Abdulkadir Gungor
Author-email: abdulkadir_gungor@outlook.com
Keywords: python,python3,Turkish,Turkish,hello,gungor,an example package
Classifier: Development Status :: 1 - Planning
Classifier: Intended Audience :: Developers
Classifier: Programming Language :: Python :: 3
Classifier: Operating System :: Microsoft :: Windows
